yugal.py
yugal-8.1.0.dist-info/METADATA
yugal-8.1.0.dist-info/WHEEL
yugal-8.1.0.dist-info/entry_points.txt
yugal-8.1.0.dist-info/top_level.txt
yugal-8.1.0.dist-info/RECORD
