Metadata-Version: 2.1
Name: yugal
Version: 8.1.0
Summary: Yugal CLI
Home-page: UNKNOWN
Author: Paurush Sinha
Author-email: stuff.random.in@gmail.com
License: UNKNOWN
Platform: UNKNOWN
